pytest_pipeline/core.py
pytest_pipeline/utils.py
pytest_pipeline/plugin.py
pytest_pipeline/mark.py
pytest_pipeline/__init__.py
pytest_pipeline-0.1.0.dist-info/metadata.json
pytest_pipeline-0.1.0.dist-info/DESCRIPTION.rst
pytest_pipeline-0.1.0.dist-info/top_level.txt
pytest_pipeline-0.1.0.dist-info/entry_points.txt
pytest_pipeline-0.1.0.dist-info/METADATA
pytest_pipeline-0.1.0.dist-info/RECORD
pytest_pipeline-0.1.0.dist-info/WHEEL
