Metadata-Version: 2.0
Name: pytest-pipeline
Version: 0.1.0
Summary: Pytest plugin for functional testing of data analysis pipelines
Home-page: https://github.com/bow/pytest_pipeline
Author: Wibowo Arindrarto
Author-email: bow@bow.web.id
License: BSD
Keywords: pytest pipeline plugin testing
Platform: UNKNOWN
Classifier: Development Status :: 3 - Alpha
Classifier: Environment :: Console
Classifier: Intended Audience :: Developers
Classifier: License :: OSI Approved :: BSD License
Classifier: Operating System :: POSIX
Classifier: Programming Language :: Python :: 2.7
Classifier: Programming Language :: Python :: 3.3
Classifier: Programming Language :: Python :: 3.4
Classifier: Topic :: Utilities
Classifier: Topic :: Software Development :: Testing
Classifier: Topic :: Software Development :: Libraries
Requires-Dist: future (==0.13.0)
Requires-Dist: pytest (>=2.6.0)
Requires-Dist: wheel (==0.23.0)
